astro_reduce.py
cosmetic.py
helpers.py
astro_reduce-5.1.1.data/data/data/astrometry.cfg
astro_reduce-5.1.1.data/data/data/default.conv
astro_reduce-5.1.1.data/data/data/t120-andor1024.ahead
astro_reduce-5.1.1.data/data/data/t120.param
astro_reduce-5.1.1.data/data/data/t120.parampsfex
astro_reduce-5.1.1.data/data/data/t120.psfex
astro_reduce-5.1.1.data/data/data/t120.scamp
astro_reduce-5.1.1.data/data/data/t120.sex
astro_reduce-5.1.1.dist-info/LICENSE
astro_reduce-5.1.1.dist-info/METADATA
astro_reduce-5.1.1.dist-info/WHEEL
astro_reduce-5.1.1.dist-info/entry_points.txt
astro_reduce-5.1.1.dist-info/top_level.txt
astro_reduce-5.1.1.dist-info/RECORD
