Metadata-Version: 2.1
Name: astro-reduce
Version: 5.1.1
Summary: A simple CCD-image reducer for the Observatoire de Paris-Meudon.
Home-page: https://gitlab.com/vaubaill/astro_reduce
Author: Raphaël Duque, Jeremie Vaubaillon
Author-email: vaubaill@imcce.fr
License: MIT
Keywords: astronomy reduction images automatic astrometry
Platform: UNKNOWN
Classifier: Environment :: Console
Classifier: Programming Language :: Python :: 3.0
Classifier: License :: OSI Approved :: MIT License
Classifier: Operating System :: Unix
Classifier: Topic :: Scientific/Engineering :: Astronomy
Requires-Python: >=3.0
Requires-Dist: astropy
Requires-Dist: astroquery
Requires-Dist: click
Requires-Dist: matplotlib
Requires-Dist: numpy
Requires-Dist: scipy
